SmileRating/resources_rc.py
SmileRating/smilerating.py
SmileRating/smilerating_demo.py
SmileRating/test_smilerating.py
SmileRating/test_smilerating_bot.py
SmileRating-0.1.dist-info/LICENSE.txt
SmileRating-0.1.dist-info/METADATA
SmileRating-0.1.dist-info/WHEEL
SmileRating-0.1.dist-info/top_level.txt
SmileRating-0.1.dist-info/RECORD
